bbm92_cw/SKR.py
bbm92_cw/__init__.py
bbm92_cw/example/example_figures.py
bbm92_cw/example/example_overpass.py
bbm92_cw-0.0.2.dist-info/LICENSE
bbm92_cw-0.0.2.dist-info/METADATA
bbm92_cw-0.0.2.dist-info/WHEEL
bbm92_cw-0.0.2.dist-info/top_level.txt
bbm92_cw-0.0.2.dist-info/RECORD
