Metadata-Version: 2.1
Name: bbm92_cw
Version: 0.0.2
Summary: Python package that allows to model the expected keyrates in a BBM92 protocol based on SPDC pumped with a CW laser.
Author-email: Thomas Jaeken <tj2022@hw.ac.uk>
Project-URL: Bug Tracker, https://github.com/Thomas-Jaeken/BBM92_CW/issues
Project-URL: Homepage, https://github.com/Thomas-Jaeken/BBM92_CW
Classifier: Programming Language :: Python :: 3
Classifier: License :: OSI Approved :: Apache Software License
Classifier: Operating System :: OS Independent
Requires-Python: >=3.7
License-File: LICENSE
